[
    {
        "name":"Sleeping",
        "duah":"اللَّهُمَّ بِاسْمِكَ أَمُوتُ وَأَحْيَا",
        "transliteration":"Allahumma Bismika Amutu W'Ahiya",
        "translation": "O Allah, by Your name I live and die.",
        "reference":"Bukhari, Muslim",
        "audio":"sleeping.mp3"
    },
    {
        "name":"Awakening",
        "duah":"الْحَمْدُ لِلَّهِ الَّذِي أَحْيَانَا بَعْدَ مَا أَمَاتَنَا وَإِلَيْهِ النُّشُورُ",
        "transliteration":"Alhamdulillah hillazi, Ahyana Ba'dam Amatana, Wa Ilahin Nushur",
        "translation": "All praise be to Allah, who gave us life after killing us (sleep is a form of death) and to Him will we be raised and returned",
        "reference":"Bukhari, Muslim"
    },
    {
        "name":"Dua for illness",
        "duah":"",
        "transliteration":"Allahumma inni aouthubika min albaras wal junun wal judam wa min sayeeil asqaam",
        "translation": "O Allah I seek your refuge from leprosy,insanity,mutilation and from all serious illnesses ",
        "reference":"Sunan ibn Dawood"
    }
    ,{
        "name":"Toilet Dua",
        "duah":"اللَّهُـمَّ إِنِّي أَعُـوذُ بِـكَ مِـنَ الْخُـبْثِ وَالْخَبَائِثِ.",
        "transliteration":"allahumma innee aAAoothu bika minal-khubthi wal-khaba-ith",      
        "translation":"O Allah, I take refuge with you from all evil and evil-doers.",
        "reference":"Al-Bukhari 1:45, Muslim 1:283"
        
    }    
    ,{
      "name":"Dua for Anger",
      "duah":"اللَّهُمَّ أَذْهِبْ غَيْظَ قَلْبِي",
      "transliteration":"Allahumma azhib Gaydha Qalbee.",      
      "translation":"Oh Allah, remove anger from my heart."
      
    }
   ,{
    "name":"Dua for Negativity",
    "duah":"اللهم اغسلني من السلبية ", 
    "transliteration":"Allahumma iGsilnee min assalbiyah ",
    "translation":"Oh Allah wash away my negativity."
   }
]


